Metadata-Version: 2.1
Name: projectile-opt-package
Version: 0.0.2
Summary: Special CAD Library
Author-email: denisdoronichev86@mail.ru
